pyflybygen/__about__.py
pyflybygen/__init__.py
pyflybygen/config.py
pyflybygen/console.py
pyflybygen/pyflybygen.py
pyflybygen/standard_config.py
pyflybygen/cli/__init__.py
pyflybygen/cli/app.py
pyflybygen/cli/common.py
pyflybygen/cli/config.py
pyflybygen/cli/tui.py
pyflybygen/tui/app.css
pyflybygen/tui/app.py
pyflybygen-0.2.0.dist-info/METADATA
pyflybygen-0.2.0.dist-info/WHEEL
pyflybygen-0.2.0.dist-info/entry_points.txt
pyflybygen-0.2.0.dist-info/licenses/LICENSE.txt
pyflybygen-0.2.0.dist-info/RECORD
